{
  "_class": "shapePath",
  "booleanOperation": -1,
  "do_objectID": "01D04AD3-ABED-41BD-96F9-F1D26BDE3F01",
  "edited": true,
  "exportOptions": {
    "_class": "exportOptions",
    "do_objectID": "BB8839C4-91C9-44B3-8882-8FEA7B715767",
    "exportFormats": [
    ],
    "includedLayerIds": [
    ],
    "layerOptions": 0,
    "shouldTrim": false
  },
  "frame": {
    "_class": "rect",
    "constrainProportions": false,
    "do_objectID": "FD8BF538-DAC1-4524-B8C1-159D3FC5DD22",
    "height": 14,
    "width": 0.8292682926829285,
    "x": 0,
    "y": 0
  },
  "isClosed": false,
  "isFixedToViewport": false,
  "isFlippedHorizontal": false,
  "isFlippedVertical": false,
  "isLocked": false,
  "isVisible": true,
  "layerListExpandedType": 0,
  "name": "Path",
  "nameIsFixed": false,
  "pointRadiusBehaviour": 0,
  "points": [
    {
      "_class": "curvePoint",
      "cornerRadius": 0,
      "curveFrom": "{0.49999999999999956, 1}",
      "curveMode": 1,
      "curveTo": "{0.49999999999999956, 1}",
      "hasCurveFrom": false,
      "hasCurveTo": false,
      "point": "{0.49999999999999956, 1}"
    },
    {
      "_class": "curvePoint",
      "cornerRadius": 0,
      "curveFrom": "{0.50000000000000056, 0}",
      "curveMode": 1,
      "curveTo": "{0.50000000000000056, 0}",
      "hasCurveFrom": false,
      "hasCurveTo": false,
      "point": "{0.50000000000000056, 0}"
    }
  ],
  "resizingConstraint": 63,
  "resizingType": 0,
  "rotation": 0,
  "shouldBreakMaskChain": false
}