{
  "_class": "shapeGroup",
  "booleanOperation": 0,
  "clippingMaskMode": 0,
  "do_objectID": "F13ECCB2-5FE2-4BBF-886A-DD0B841AC4E9",
  "exportOptions": {
    "_class": "exportOptions",
    "do_objectID": "659B0268-EBF8-4B2E-A644-A83D5EE2D074",
    "exportFormats": [
    ],
    "includedLayerIds": [
    ],
    "layerOptions": 0,
    "shouldTrim": false
  },
  "frame": {
    "_class": "rect",
    "constrainProportions": false,
    "do_objectID": "ABA7ACEB-F9B4-494A-A540-7DFA6AAB140B",
    "height": 17.06666666666667,
    "width": 320,
    "x": 0,
    "y": 0
  },
  "hasClickThrough": false,
  "hasClippingMask": false,
  "isFixedToViewport": false,
  "isFlippedHorizontal": false,
  "isFlippedVertical": false,
  "isLocked": false,
  "isVisible": true,
  "layerListExpandedType": 0,
  "layers": [
    {
      "class": "rectangle",
      "id": "6003643B-691B-4080-A883-E4C9BF6F0A01"
    }
  ],
  "name": "Background",
  "nameIsFixed": true,
  "originalObjectID": "AD645A32-DDA4-4BED-A99A-8EB6D85B69E7",
  "resizingConstraint": 63,
  "resizingType": 0,
  "rotation": 0,
  "shouldBreakMaskChain": false,
  "style": {
    "_class": "style",
    "blur": {
      "_class": "blur",
      "center": "{0.5, 0.5}",
      "do_objectID": "1D8404FD-2C43-4E3E-A7C8-04DA32BF054A",
      "isEnabled": false,
      "motionAngle": 0,
      "radius": 8.533333333333333,
      "type": 0
    },
    "do_objectID": "F2553EDF-D214-4D14-8486-44901543B887",
    "endMarkerType": 0,
    "fills": [
      {
        "_class": "fill",
        "color": {
          "_class": "color",
          "alpha": 1,
          "blue": 0.9725490196078431,
          "green": 0.9725490196078431,
          "red": 0.9725490196078431
        },
        "fillType": 0,
        "isEnabled": true,
        "noiseIndex": 0,
        "noiseIntensity": 0,
        "patternFillType": 0,
        "patternTileScale": 1
      }
    ],
    "miterLimit": 10,
    "startMarkerType": 0,
    "windingRule": 1
  },
  "windingRule": 1
}